researchai/__init__.py
researchai/_modidx.py
researchai/nn/__init__.py
researchai/nn/layers.py
researchai-0.0.1.dist-info/LICENSE
researchai-0.0.1.dist-info/METADATA
researchai-0.0.1.dist-info/WHEEL
researchai-0.0.1.dist-info/entry_points.txt
researchai-0.0.1.dist-info/top_level.txt
researchai-0.0.1.dist-info/RECORD
